[
  [
    {
      "sketch_op": "Line",
      "start": [
        0.023,
        -0.005
      ],
      "end": [
        0.051,
        -0.005
      ]
    },
    {
      "sketch_op": "Line",
      "start": [
        0.051,
        -0.005
      ],
      "end": [
        0.051,
        -0.015
      ]
    },
    {
      "sketch_op": "Line",
      "start": [
        0.051,
        -0.015
      ],
      "end": [
        0.056,
        -0.015
      ]
    },
    {
      "sketch_op": "Line",
      "start": [
        0.056,
        -0.015
      ],
      "end": [
        0.056,
        0.01
      ]
    },
    {
      "sketch_op": "Line",
      "start": [
        0.056,
        0.01
      ],
      "end": [
        0.051,
        0.01
      ]
    },
    {
      "sketch_op": "Line",
      "start": [
        0.051,
        0.01
      ],
      "end": [
        0.051,
        0.0
      ]
    },
    {
      "sketch_op": "Line",
      "start": [
        0.051,
        0.0
      ],
      "end": [
        0.023,
        0.0
      ]
    },
    {
      "sketch_op": "Line",
      "start": [
        0.023,
        0.0
      ],
      "end": [
        0.023,
        -0.005
      ]
    }
  ]
]