[
  {
    "kind": "NodeOp",
    "label": "External",
    "parameters": {}
  },
  {
    "kind": "NodeOp",
    "label": "Line",
    "parameters": {
      "isConstruction": false,
      "dirX": 1.0,
      "dirY": 0.0,
      "pntX": -0.0010650488547980785,
      "pntY": 0.0,
      "startParam": -0.0049349511452019285,
      "endParam": 0.007065048854798086
    }
  },
  {
    "kind": "NodeOp",
    "label": "SN_Start",
    "parameters": {}
  },
  {
    "kind": "EdgeOp",
    "label": "Horizontal",
    "references": "(2, 0)",
    "parameters": {}
  },
  {
    "kind": "NodeOp",
    "label": "SN_End",
    "parameters": {}
  },
  {
    "kind": "EdgeOp",
    "label": "Midpoint",
    "references": "(3, 2, 0)",
    "parameters": {}
  },
  {
    "kind": "NodeOp",
    "label": "Line",
    "parameters": {
      "isConstruction": false,
      "dirX": 1.0,
      "dirY": 0.0,
      "pntX": 0.0006883810795843496,
      "pntY": 0.168,
      "startParam": -0.00668838107958436,
      "endParam": 0.005311618920415661
    }
  },
  {
    "kind": "EdgeOp",
    "label": "Parallel",
    "references": "(4, 1)",
    "parameters": {}
  },
  {
    "kind": "EdgeOp",
    "label": "Horizontal",
    "references": "(4,)",
    "parameters": {}
  },
  {
    "kind": "NodeOp",
    "label": "SN_Start",
    "parameters": {}
  },
  {
    "kind": "NodeOp",
    "label": "SN_End",
    "parameters": {}
  },
  {
    "kind": "NodeOp",
    "label": "Line",
    "parameters": {
      "isConstruction": false,
      "dirX": 6.123233995736765e-17,
      "dirY": 1.0,
      "pntX": -0.006000000000000005,
      "pntY": 0.027103682979941368,
      "startParam": -0.027103682979941368,
      "endParam": 0.14089631702005864
    }
  },
  {
    "kind": "EdgeOp",
    "label": "Perpendicular",
    "references": "(7, 4)",
    "parameters": {}
  },
  {
    "kind": "NodeOp",
    "label": "SN_Start",
    "parameters": {}
  },
  {
    "kind": "EdgeOp",
    "label": "Coincident",
    "references": "(8, 2)",
    "parameters": {}
  },
  {
    "kind": "NodeOp",
    "label": "SN_End",
    "parameters": {}
  },
  {
    "kind": "EdgeOp",
    "label": "Coincident",
    "references": "(9, 5)",
    "parameters": {}
  },
  {
    "kind": "NodeOp",
    "label": "Line",
    "parameters": {
      "isConstruction": false,
      "dirX": 6.123233995736762e-17,
      "dirY": 1.0,
      "pntX": 0.005999999999999995,
      "pntY": 0.027103682979941365,
      "startParam": -0.027103682979941365,
      "endParam": 0.14089631702005864
    }
  },
  {
    "kind": "EdgeOp",
    "label": "Parallel",
    "references": "(10, 7)",
    "parameters": {}
  },
  {
    "kind": "NodeOp",
    "label": "SN_Start",
    "parameters": {}
  },
  {
    "kind": "EdgeOp",
    "label": "Coincident",
    "references": "(11, 3)",
    "parameters": {}
  },
  {
    "kind": "NodeOp",
    "label": "SN_End",
    "parameters": {}
  },
  {
    "kind": "EdgeOp",
    "label": "Coincident",
    "references": "(12, 6)",
    "parameters": {}
  },
  {
    "kind": "NodeOp",
    "label": "Line",
    "parameters": {
      "isConstruction": true,
      "dirX": 0.0,
      "dirY": 1.0,
      "pntX": 0.0,
      "pntY": 0.084,
      "startParam": -0.084,
      "endParam": 0.084
    }
  },
  {
    "kind": "NodeOp",
    "label": "SN_Start",
    "parameters": {}
  },
  {
    "kind": "EdgeOp",
    "label": "Coincident",
    "references": "(14, 0)",
    "parameters": {}
  },
  {
    "kind": "NodeOp",
    "label": "SN_End",
    "parameters": {}
  },
  {
    "kind": "EdgeOp",
    "label": "Midpoint",
    "references": "(15, 4)",
    "parameters": {}
  },
  {
    "kind": "NodeOp",
    "label": "Circle",
    "parameters": {
      "isConstruction": false,
      "clockwise": false,
      "xCenter": 0.0,
      "yCenter": 0.14800000000000002,
      "xDir": 1.0,
      "yDir": 0.0,
      "radius": 0.0025
    }
  },
  {
    "kind": "EdgeOp",
    "label": "Diameter",
    "references": "(16,)",
    "parameters": {
      "length": "0.005 METER"
    }
  },
  {
    "kind": "NodeOp",
    "label": "SN_Center",
    "parameters": {}
  },
  {
    "kind": "EdgeOp",
    "label": "Coincident",
    "references": "(17, 13)",
    "parameters": {}
  },
  {
    "kind": "NodeOp",
    "label": "Circle",
    "parameters": {
      "isConstruction": false,
      "clockwise": false,
      "xCenter": 0.0,
      "yCenter": 0.02,
      "xDir": 1.0,
      "yDir": 0.0,
      "radius": 0.0025
    }
  },
  {
    "kind": "EdgeOp",
    "label": "Equal",
    "references": "(18, 16)",
    "parameters": {}
  },
  {
    "kind": "NodeOp",
    "label": "SN_Center",
    "parameters": {}
  },
  {
    "kind": "EdgeOp",
    "label": "Coincident",
    "references": "(19, 13)",
    "parameters": {}
  },
  {
    "kind": "NodeOp",
    "label": "Stop",
    "parameters": {}
  }
]