[
  [
    {
      "sketch_op": "Line",
      "start": [
        -4.06997,
        0.05
      ],
      "end": [
        -3.06997,
        0.05
      ]
    },
    {
      "sketch_op": "Line",
      "start": [
        -3.06997,
        0.05
      ],
      "end": [
        -3.06997,
        -0.05
      ]
    },
    {
      "sketch_op": "Line",
      "start": [
        -3.06997,
        -0.05
      ],
      "end": [
        -4.06997,
        -0.05
      ]
    },
    {
      "sketch_op": "Line",
      "start": [
        -4.06997,
        -0.05
      ],
      "end": [
        -4.06997,
        0.05
      ]
    }
  ]
]