[
  {
    "kind": "NodeOp",
    "label": "External",
    "parameters": {}
  },
  {
    "kind": "NodeOp",
    "label": "Line",
    "parameters": {
      "isConstruction": false,
      "dirX": 1.0,
      "dirY": 0.0,
      "pntX": 0.016805929108963953,
      "pntY": 0.009978241359731101,
      "startParam": -0.003658972265780009,
      "endParam": 0.003658972265780009
    }
  },
  {
    "kind": "NodeOp",
    "label": "SN_Start",
    "parameters": {}
  },
  {
    "kind": "NodeOp",
    "label": "SN_End",
    "parameters": {}
  },
  {
    "kind": "NodeOp",
    "label": "Line",
    "parameters": {
      "isConstruction": false,
      "dirX": 1.0,
      "dirY": 0.0,
      "pntX": 0.016805929108963953,
      "pntY": 0.005928241359731103,
      "startParam": -0.003658972265780009,
      "endParam": 0.003658972265780009
    }
  },
  {
    "kind": "EdgeOp",
    "label": "Parallel",
    "references": "(4, 1)",
    "parameters": {}
  },
  {
    "kind": "EdgeOp",
    "label": "Horizontal",
    "references": "(4,)",
    "parameters": {}
  },
  {
    "kind": "NodeOp",
    "label": "SN_Start",
    "parameters": {}
  },
  {
    "kind": "NodeOp",
    "label": "SN_End",
    "parameters": {}
  },
  {
    "kind": "NodeOp",
    "label": "Line",
    "parameters": {
      "isConstruction": false,
      "dirX": 0.0,
      "dirY": -1.0,
      "pntX": 0.013146956843183944,
      "pntY": 0.007915441878139973,
      "startParam": -0.0020627994815911287,
      "endParam": 0.0019872005184088694
    }
  },
  {
    "kind": "EdgeOp",
    "label": "Perpendicular",
    "references": "(7, 4)",
    "parameters": {}
  },
  {
    "kind": "NodeOp",
    "label": "SN_Start",
    "parameters": {}
  },
  {
    "kind": "EdgeOp",
    "label": "Coincident",
    "references": "(8, 2)",
    "parameters": {}
  },
  {
    "kind": "NodeOp",
    "label": "SN_End",
    "parameters": {}
  },
  {
    "kind": "EdgeOp",
    "label": "Coincident",
    "references": "(9, 5)",
    "parameters": {}
  },
  {
    "kind": "NodeOp",
    "label": "Line",
    "parameters": {
      "isConstruction": false,
      "dirX": 6.123233995736766e-17,
      "dirY": -1.0,
      "pntX": 0.020464901374743962,
      "pntY": 0.007991040841322232,
      "startParam": -0.0019872005184088694,
      "endParam": 0.0020627994815911287
    }
  },
  {
    "kind": "EdgeOp",
    "label": "Parallel",
    "references": "(10, 7)",
    "parameters": {}
  },
  {
    "kind": "NodeOp",
    "label": "SN_Start",
    "parameters": {}
  },
  {
    "kind": "EdgeOp",
    "label": "Coincident",
    "references": "(11, 3)",
    "parameters": {}
  },
  {
    "kind": "NodeOp",
    "label": "SN_End",
    "parameters": {}
  },
  {
    "kind": "EdgeOp",
    "label": "Coincident",
    "references": "(12, 6)",
    "parameters": {}
  },
  {
    "kind": "NodeOp",
    "label": "Circle",
    "parameters": {
      "isConstruction": false,
      "clockwise": false,
      "xCenter": 0.016805929108963953,
      "yCenter": 0.007953241359731102,
      "xDir": 1.0,
      "yDir": 0.0,
      "radius": 0.00322
    }
  },
  {
    "kind": "EdgeOp",
    "label": "Diameter",
    "references": "(13,)",
    "parameters": {
      "length": "0.00644 METER"
    }
  },
  {
    "kind": "NodeOp",
    "label": "SN_Center",
    "parameters": {}
  },
  {
    "kind": "NodeOp",
    "label": "Point",
    "parameters": {
      "isConstruction": false,
      "x": 0.016805929108963953,
      "y": 0.009978241359731101
    }
  },
  {
    "kind": "EdgeOp",
    "label": "Midpoint",
    "references": "(15, 1)",
    "parameters": {}
  },
  {
    "kind": "EdgeOp",
    "label": "Vertical",
    "references": "(15, 14)",
    "parameters": {}
  },
  {
    "kind": "NodeOp",
    "label": "Point",
    "parameters": {
      "isConstruction": false,
      "x": 0.013146956843183944,
      "y": 0.007953241359731102
    }
  },
  {
    "kind": "EdgeOp",
    "label": "Midpoint",
    "references": "(16, 7)",
    "parameters": {}
  },
  {
    "kind": "EdgeOp",
    "label": "Horizontal",
    "references": "(16, 14)",
    "parameters": {}
  },
  {
    "kind": "NodeOp",
    "label": "Circle",
    "parameters": {
      "isConstruction": false,
      "clockwise": false,
      "xCenter": 0.022862158556373052,
      "yCenter": 0.007757727492621108,
      "xDir": 1.0,
      "yDir": 0.0,
      "radius": 0.000693942187589763
    }
  },
  {
    "kind": "NodeOp",
    "label": "SN_Center",
    "parameters": {}
  },
  {
    "kind": "NodeOp",
    "label": "Stop",
    "parameters": {}
  }
]