[
  {
    "kind": "NodeOp",
    "label": "External",
    "parameters": {}
  },
  {
    "kind": "NodeOp",
    "label": "Line",
    "parameters": {
      "isConstruction": false,
      "dirX": -1.0,
      "dirY": -1.2246467991473532e-16,
      "pntX": -0.006349999999999992,
      "pntY": -0.019049999999999997,
      "startParam": -0.0508,
      "endParam": 0.0381
    }
  },
  {
    "kind": "NodeOp",
    "label": "SN_Start",
    "parameters": {}
  },
  {
    "kind": "NodeOp",
    "label": "SN_End",
    "parameters": {}
  },
  {
    "kind": "NodeOp",
    "label": "Line",
    "parameters": {
      "isConstruction": false,
      "dirX": -1.0,
      "dirY": -1.2246467991473532e-16,
      "pntX": -7.215407925857655e-20,
      "pntY": 0.019050000000000004,
      "startParam": -0.044449999999999996,
      "endParam": 0.04445
    }
  },
  {
    "kind": "EdgeOp",
    "label": "Parallel",
    "references": "(4, 1)",
    "parameters": {}
  },
  {
    "kind": "EdgeOp",
    "label": "Horizontal",
    "references": "(4,)",
    "parameters": {}
  },
  {
    "kind": "NodeOp",
    "label": "SN_Start",
    "parameters": {}
  },
  {
    "kind": "NodeOp",
    "label": "SN_End",
    "parameters": {}
  },
  {
    "kind": "NodeOp",
    "label": "Line",
    "parameters": {
      "isConstruction": false,
      "dirX": -1.83697019872103e-16,
      "dirY": 1.0,
      "pntX": 0.04445,
      "pntY": -0.0005891827693405983,
      "startParam": -0.018460817230659392,
      "endParam": 0.019639182769340617
    }
  },
  {
    "kind": "EdgeOp",
    "label": "Perpendicular",
    "references": "(7, 4)",
    "parameters": {}
  },
  {
    "kind": "NodeOp",
    "label": "SN_Start",
    "parameters": {}
  },
  {
    "kind": "EdgeOp",
    "label": "Coincident",
    "references": "(8, 2)",
    "parameters": {}
  },
  {
    "kind": "NodeOp",
    "label": "SN_End",
    "parameters": {}
  },
  {
    "kind": "EdgeOp",
    "label": "Coincident",
    "references": "(9, 5)",
    "parameters": {}
  },
  {
    "kind": "NodeOp",
    "label": "Line",
    "parameters": {
      "isConstruction": false,
      "dirX": -1.8369701987210297e-16,
      "dirY": 1.0,
      "pntX": -0.04445,
      "pntY": -0.0005891827693406111,
      "startParam": -0.01846081723065939,
      "endParam": 0.01963918276934062
    }
  },
  {
    "kind": "EdgeOp",
    "label": "Parallel",
    "references": "(10, 7)",
    "parameters": {}
  },
  {
    "kind": "NodeOp",
    "label": "SN_Start",
    "parameters": {}
  },
  {
    "kind": "EdgeOp",
    "label": "Coincident",
    "references": "(11, 3)",
    "parameters": {}
  },
  {
    "kind": "NodeOp",
    "label": "SN_End",
    "parameters": {}
  },
  {
    "kind": "EdgeOp",
    "label": "Coincident",
    "references": "(12, 6)",
    "parameters": {}
  },
  {
    "kind": "NodeOp",
    "label": "Point",
    "parameters": {
      "isConstruction": false,
      "x": 0.0,
      "y": 0.0
    }
  },
  {
    "kind": "EdgeOp",
    "label": "Midpoint",
    "references": "(13, 5, 3)",
    "parameters": {}
  },
  {
    "kind": "EdgeOp",
    "label": "Midpoint",
    "references": "(13, 6, 2)",
    "parameters": {}
  },
  {
    "kind": "EdgeOp",
    "label": "Coincident",
    "references": "(13, 0)",
    "parameters": {}
  },
  {
    "kind": "NodeOp",
    "label": "Stop",
    "parameters": {}
  }
]