[
  [
    {
      "sketch_op": "Circle",
      "center": [
        0.0,
        0.0
      ],
      "radius": 0.00953
    }
  ],
  [
    {
      "sketch_op": "Circle",
      "center": [
        0.0,
        0.0
      ],
      "radius": 0.0127
    }
  ],
  [
    {
      "sketch_op": "Circle",
      "center": [
        -0.0,
        0.04286
      ],
      "radius": 0.00794
    }
  ],
  [
    {
      "sketch_op": "Circle",
      "center": [
        -0.0,
        0.04286
      ],
      "radius": 0.00476
    }
  ]
]