[
  [
    {
      "sketch_op": "Line",
      "start": [
        0.03251,
        0.0
      ],
      "end": [
        0.03251,
        0.2286
      ]
    },
    {
      "sketch_op": "Line",
      "start": [
        0.03251,
        0.2286
      ],
      "end": [
        0.03302,
        0.2286
      ]
    },
    {
      "sketch_op": "Line",
      "start": [
        0.03302,
        0.2286
      ],
      "end": [
        0.03302,
        0.0
      ]
    },
    {
      "sketch_op": "Line",
      "start": [
        0.03302,
        0.0
      ],
      "end": [
        0.03251,
        0.0
      ]
    }
  ],
  [
    {
      "sketch_op": "Line",
      "start": [
        0.0,
        0.0
      ],
      "end": [
        0.0,
        0.2286
      ]
    },
    {
      "sketch_op": "Line",
      "start": [
        0.0,
        0.2286
      ],
      "end": [
        0.03251,
        0.2286
      ]
    },
    {
      "sketch_op": "Line",
      "start": [
        0.03251,
        0.2286
      ],
      "end": [
        0.03251,
        0.0
      ]
    },
    {
      "sketch_op": "Line",
      "start": [
        0.03251,
        0.0
      ],
      "end": [
        0.0,
        0.0
      ]
    }
  ]
]