[
  [
    {
      "sketch_op": "Arc",
      "start": [
        -0.00215,
        0.06141
      ],
      "mid": [
        -0.00152,
        0.06194
      ],
      "end": [
        -0.00129,
        0.06273
      ]
    },
    {
      "sketch_op": "Line",
      "start": [
        -0.00129,
        0.06273
      ],
      "end": [
        -0.00148,
        0.06275
      ]
    },
    {
      "sketch_op": "Arc",
      "start": [
        -0.00148,
        0.06275
      ],
      "mid": [
        -0.00165,
        0.062
      ],
      "end": [
        -0.00223,
        0.0615
      ]
    },
    {
      "sketch_op": "Line",
      "start": [
        -0.00223,
        0.0615
      ],
      "end": [
        -0.00215,
        0.06141
      ]
    }
  ],
  [
    {
      "sketch_op": "Arc",
      "start": [
        -0.00205,
        0.05957
      ],
      "mid": [
        -0.00194,
        0.06037
      ],
      "end": [
        -0.00233,
        0.06106
      ]
    },
    {
      "sketch_op": "Line",
      "start": [
        -0.00233,
        0.06106
      ],
      "end": [
        -0.00246,
        0.06106
      ]
    },
    {
      "sketch_op": "Arc",
      "start": [
        -0.00246,
        0.06106
      ],
      "mid": [
        -0.00209,
        0.06036
      ],
      "end": [
        -0.00225,
        0.05957
      ]
    },
    {
      "sketch_op": "Line",
      "start": [
        -0.00225,
        0.05957
      ],
      "end": [
        -0.00205,
        0.05957
      ]
    }
  ]
]