[
  [
    {
      "sketch_op": "Line",
      "start": [
        -0.02,
        0.22196
      ],
      "end": [
        0.02,
        0.22196
      ]
    },
    {
      "sketch_op": "Line",
      "start": [
        0.02,
        0.22196
      ],
      "end": [
        0.02,
        0.12196
      ]
    },
    {
      "sketch_op": "Line",
      "start": [
        0.02,
        0.12196
      ],
      "end": [
        -0.02,
        0.12196
      ]
    },
    {
      "sketch_op": "Line",
      "start": [
        -0.02,
        0.12196
      ],
      "end": [
        -0.02,
        0.22196
      ]
    }
  ]
]