[
  {
    "kind": "NodeOp",
    "label": "External",
    "parameters": {}
  },
  {
    "kind": "NodeOp",
    "label": "Line",
    "parameters": {
      "isConstruction": false,
      "dirX": 0.0,
      "dirY": -1.0,
      "pntX": 0.0,
      "pntY": 0.00016291067039506539,
      "startParam": -0.0022183393296049347,
      "endParam": 0.002544160670395066
    }
  },
  {
    "kind": "EdgeOp",
    "label": "Vertical",
    "references": "(1,)",
    "parameters": {}
  },
  {
    "kind": "NodeOp",
    "label": "SN_Start",
    "parameters": {}
  },
  {
    "kind": "EdgeOp",
    "label": "Vertical",
    "references": "(2, 0)",
    "parameters": {}
  },
  {
    "kind": "NodeOp",
    "label": "SN_End",
    "parameters": {}
  },
  {
    "kind": "NodeOp",
    "label": "Arc",
    "parameters": {
      "isConstruction": false,
      "clockwise": true,
      "xCenter": 0.0,
      "yCenter": 0.0,
      "xDir": 1.0,
      "yDir": 0.0,
      "radius": 0.0023812500000000006,
      "startParam": -1.5707963267948966,
      "endParam": 1.5707963267948966
    }
  },
  {
    "kind": "EdgeOp",
    "label": "Radius",
    "references": "(4,)",
    "parameters": {
      "length": "0.002381 METER"
    }
  },
  {
    "kind": "EdgeOp",
    "label": "Coincident",
    "references": "(4, 3)",
    "parameters": {}
  },
  {
    "kind": "NodeOp",
    "label": "SN_Center",
    "parameters": {}
  },
  {
    "kind": "EdgeOp",
    "label": "Coincident",
    "references": "(5, 0)",
    "parameters": {}
  },
  {
    "kind": "NodeOp",
    "label": "SN_Start",
    "parameters": {}
  },
  {
    "kind": "EdgeOp",
    "label": "Coincident",
    "references": "(6, 2)",
    "parameters": {}
  },
  {
    "kind": "NodeOp",
    "label": "SN_End",
    "parameters": {}
  },
  {
    "kind": "EdgeOp",
    "label": "Vertical",
    "references": "(7, 2)",
    "parameters": {}
  },
  {
    "kind": "NodeOp",
    "label": "Stop",
    "parameters": {}
  }
]