[
  [
    {
      "sketch_op": "Circle",
      "center": [
        -4.17743,
        0.7867
      ],
      "radius": 0.75
    }
  ],
  [
    {
      "sketch_op": "Line",
      "start": [
        -4.17963,
        -1.3566
      ],
      "end": [
        -2.97963,
        -1.3566
      ]
    },
    {
      "sketch_op": "Line",
      "start": [
        -2.97963,
        -1.3566
      ],
      "end": [
        -2.97963,
        -0.9566
      ]
    },
    {
      "sketch_op": "Line",
      "start": [
        -2.97963,
        -0.9566
      ],
      "end": [
        -4.17963,
        -0.9566
      ]
    },
    {
      "sketch_op": "Line",
      "start": [
        -4.17963,
        -0.9566
      ],
      "end": [
        -4.17963,
        -1.3566
      ]
    }
  ],
  [
    {
      "sketch_op": "Line",
      "start": [
        -6.87007,
        -0.80587
      ],
      "end": [
        -6.07033,
        -1.26064
      ]
    },
    {
      "sketch_op": "Line",
      "start": [
        -6.07033,
        -1.26064
      ],
      "end": [
        -5.71442,
        -0.63476
      ]
    },
    {
      "sketch_op": "Line",
      "start": [
        -5.71442,
        -0.63476
      ],
      "end": [
        -6.51416,
        -0.17999
      ]
    },
    {
      "sketch_op": "Line",
      "start": [
        -6.51416,
        -0.17999
      ],
      "end": [
        -6.87007,
        -0.80587
      ]
    }
  ]
]