[
  [
    {
      "sketch_op": "Circle",
      "center": [
        0.0,
        0.0
      ],
      "radius": 0.0381
    }
  ],
  [
    {
      "sketch_op": "Circle",
      "center": [
        0.9652,
        0.19812
      ],
      "radius": 0.0381
    }
  ],
  [
    {
      "sketch_op": "Arc",
      "start": [
        -0.01277,
        0.0622
      ],
      "mid": [
        -0.06317,
        -0.00642
      ],
      "end": [
        -0.0,
        -0.0635
      ]
    },
    {
      "sketch_op": "Line",
      "start": [
        0.0,
        -0.0635
      ],
      "end": [
        0.9652,
        -0.0635
      ]
    },
    {
      "sketch_op": "Arc",
      "start": [
        0.9652,
        -0.0635
      ],
      "mid": [
        1.0101,
        -0.0449
      ],
      "end": [
        1.0287,
        0.0
      ]
    },
    {
      "sketch_op": "Line",
      "start": [
        1.0287,
        0.0
      ],
      "end": [
        1.0287,
        0.19812
      ]
    },
    {
      "sketch_op": "Arc",
      "start": [
        1.0287,
        0.19812
      ],
      "mid": [
        1.00533,
        0.24733
      ],
      "end": [
        0.95243,
        0.26032
      ]
    },
    {
      "sketch_op": "Line",
      "start": [
        0.95243,
        0.26032
      ],
      "end": [
        -0.01277,
        0.0622
      ]
    }
  ]
]