[
  [
    {
      "sketch_op": "Circle",
      "center": [
        0.00254,
        0.00254
      ],
      "radius": 0.0016
    }
  ],
  [
    {
      "sketch_op": "Circle",
      "center": [
        0.00254,
        0.05588
      ],
      "radius": 0.0016
    }
  ],
  [
    {
      "sketch_op": "Circle",
      "center": [
        0.07874,
        0.00254
      ],
      "radius": 0.0016
    }
  ],
  [
    {
      "sketch_op": "Circle",
      "center": [
        0.07874,
        0.05588
      ],
      "radius": 0.0016
    }
  ],
  [
    {
      "sketch_op": "Line",
      "start": [
        0.0,
        0.0
      ],
      "end": [
        0.08128,
        0.0
      ]
    },
    {
      "sketch_op": "Line",
      "start": [
        0.08128,
        0.0
      ],
      "end": [
        0.08128,
        0.05842
      ]
    },
    {
      "sketch_op": "Line",
      "start": [
        0.08128,
        0.05842
      ],
      "end": [
        -0.0,
        0.05842
      ]
    },
    {
      "sketch_op": "Line",
      "start": [
        0.0,
        0.05842
      ],
      "end": [
        0.0,
        0.0
      ]
    }
  ]
]