[
  [
    {
      "sketch_op": "Line",
      "start": [
        0.28417,
        1.20211
      ],
      "end": [
        -0.60583,
        1.20211
      ]
    },
    {
      "sketch_op": "Line",
      "start": [
        -0.60583,
        1.20211
      ],
      "end": [
        -0.60583,
        0.78711
      ]
    },
    {
      "sketch_op": "Line",
      "start": [
        -0.60583,
        0.78711
      ],
      "end": [
        0.28417,
        0.78711
      ]
    },
    {
      "sketch_op": "Line",
      "start": [
        0.28417,
        0.78711
      ],
      "end": [
        0.28417,
        1.20211
      ]
    }
  ],
  [
    {
      "sketch_op": "Line",
      "start": [
        -0.64083,
        0.74211
      ],
      "end": [
        0.31917,
        0.74211
      ]
    },
    {
      "sketch_op": "Arc",
      "start": [
        0.31917,
        0.74211
      ],
      "mid": [
        0.32624,
        0.74504
      ],
      "end": [
        0.32917,
        0.75211
      ]
    },
    {
      "sketch_op": "Line",
      "start": [
        0.32917,
        0.75211
      ],
      "end": [
        0.32917,
        1.23711
      ]
    },
    {
      "sketch_op": "Arc",
      "start": [
        0.32917,
        1.23711
      ],
      "mid": [
        0.32624,
        1.24419
      ],
      "end": [
        0.31917,
        1.24711
      ]
    },
    {
      "sketch_op": "Line",
      "start": [
        0.31917,
        1.24711
      ],
      "end": [
        -0.64083,
        1.24711
      ]
    },
    {
      "sketch_op": "Arc",
      "start": [
        -0.64083,
        1.24711
      ],
      "mid": [
        -0.64791,
        1.24419
      ],
      "end": [
        -0.65083,
        1.23711
      ]
    },
    {
      "sketch_op": "Line",
      "start": [
        -0.65083,
        1.23711
      ],
      "end": [
        -0.65083,
        0.75211
      ]
    },
    {
      "sketch_op": "Arc",
      "start": [
        -0.65083,
        0.75211
      ],
      "mid": [
        -0.64791,
        0.74504
      ],
      "end": [
        -0.64083,
        0.74211
      ]
    }
  ]
]