[
  [
    {
      "sketch_op": "Line",
      "start": [
        0.0,
        0.0
      ],
      "end": [
        0.0,
        0.0949
      ]
    },
    {
      "sketch_op": "Line",
      "start": [
        0.0,
        0.0949
      ],
      "end": [
        0.025,
        0.0949
      ]
    },
    {
      "sketch_op": "Line",
      "start": [
        0.025,
        0.0949
      ],
      "end": [
        0.025,
        0.03715
      ]
    },
    {
      "sketch_op": "Line",
      "start": [
        0.025,
        0.03715
      ],
      "end": [
        0.04598,
        0.01215
      ]
    },
    {
      "sketch_op": "Line",
      "start": [
        0.04598,
        0.01215
      ],
      "end": [
        0.04598,
        -0.0
      ]
    },
    {
      "sketch_op": "Line",
      "start": [
        0.04598,
        0.0
      ],
      "end": [
        0.0,
        0.0
      ]
    }
  ]
]