[
  [
    {
      "sketch_op": "Line",
      "start": [
        0.00082,
        0.00634
      ],
      "end": [
        0.00472,
        0.00431
      ]
    },
    {
      "sketch_op": "Line",
      "start": [
        0.00472,
        0.00431
      ],
      "end": [
        0.00358,
        0.00211
      ]
    },
    {
      "sketch_op": "Arc",
      "start": [
        0.00358,
        0.00211
      ],
      "mid": [
        0.00349,
        0.00205
      ],
      "end": [
        0.0034,
        0.0021
      ]
    },
    {
      "sketch_op": "Arc",
      "start": [
        0.0034,
        0.0021
      ],
      "mid": [
        0.00185,
        0.00355
      ],
      "end": [
        -0.00023,
        0.00399
      ]
    },
    {
      "sketch_op": "Arc",
      "start": [
        -0.00023,
        0.00399
      ],
      "mid": [
        -0.00032,
        0.00404
      ],
      "end": [
        -0.00032,
        0.00414
      ]
    },
    {
      "sketch_op": "Line",
      "start": [
        -0.00032,
        0.00414
      ],
      "end": [
        0.00082,
        0.00634
      ]
    }
  ]
]