[
  {
    "kind": "NodeOp",
    "label": "External",
    "parameters": {}
  },
  {
    "kind": "NodeOp",
    "label": "Line",
    "parameters": {
      "isConstruction": false,
      "dirX": 1.0,
      "dirY": 0.0,
      "pntX": -0.10196161642670631,
      "pntY": -0.07600000000000001,
      "startParam": -0.0035811476409435272,
      "endParam": 0.21641885235905645
    }
  },
  {
    "kind": "NodeOp",
    "label": "SN_Start",
    "parameters": {}
  },
  {
    "kind": "EdgeOp",
    "label": "Coincident",
    "references": "(2, 0)",
    "parameters": {}
  },
  {
    "kind": "NodeOp",
    "label": "SN_End",
    "parameters": {}
  },
  {
    "kind": "EdgeOp",
    "label": "Coincident",
    "references": "(3, 0)",
    "parameters": {}
  },
  {
    "kind": "NodeOp",
    "label": "Line",
    "parameters": {
      "isConstruction": false,
      "dirX": 1.0,
      "dirY": 0.0,
      "pntX": -0.10196161642670631,
      "pntY": -0.08500000000000005,
      "startParam": -0.0035811476409435272,
      "endParam": 0.21641885235905645
    }
  },
  {
    "kind": "EdgeOp",
    "label": "Parallel",
    "references": "(4, 1)",
    "parameters": {}
  },
  {
    "kind": "EdgeOp",
    "label": "Horizontal",
    "references": "(4,)",
    "parameters": {}
  },
  {
    "kind": "NodeOp",
    "label": "SN_Start",
    "parameters": {}
  },
  {
    "kind": "NodeOp",
    "label": "SN_End",
    "parameters": {}
  },
  {
    "kind": "NodeOp",
    "label": "Line",
    "parameters": {
      "isConstruction": false,
      "dirX": 0.0,
      "dirY": -1.0,
      "pntX": -0.10554276406764984,
      "pntY": -0.0780022752583027,
      "startParam": -0.0020022752583026826,
      "endParam": 0.006997724741697353
    }
  },
  {
    "kind": "EdgeOp",
    "label": "Perpendicular",
    "references": "(7, 4)",
    "parameters": {}
  },
  {
    "kind": "NodeOp",
    "label": "SN_Start",
    "parameters": {}
  },
  {
    "kind": "EdgeOp",
    "label": "Coincident",
    "references": "(8, 2)",
    "parameters": {}
  },
  {
    "kind": "NodeOp",
    "label": "SN_End",
    "parameters": {}
  },
  {
    "kind": "EdgeOp",
    "label": "Coincident",
    "references": "(9, 5)",
    "parameters": {}
  },
  {
    "kind": "NodeOp",
    "label": "Line",
    "parameters": {
      "isConstruction": false,
      "dirX": 6.123233995736766e-17,
      "dirY": -1.0,
      "pntX": 0.11445723593235013,
      "pntY": -0.0780022752583027,
      "startParam": -0.0020022752583026826,
      "endParam": 0.006997724741697353
    }
  },
  {
    "kind": "EdgeOp",
    "label": "Parallel",
    "references": "(10, 7)",
    "parameters": {}
  },
  {
    "kind": "NodeOp",
    "label": "SN_Start",
    "parameters": {}
  },
  {
    "kind": "EdgeOp",
    "label": "Coincident",
    "references": "(11, 3)",
    "parameters": {}
  },
  {
    "kind": "NodeOp",
    "label": "SN_End",
    "parameters": {}
  },
  {
    "kind": "EdgeOp",
    "label": "Coincident",
    "references": "(12, 6)",
    "parameters": {}
  },
  {
    "kind": "NodeOp",
    "label": "Line",
    "parameters": {
      "isConstruction": false,
      "dirX": 1.0,
      "dirY": 0.0,
      "pntX": 0.004457235932350152,
      "pntY": -0.159,
      "startParam": -0.10999999999999999,
      "endParam": 0.10999999999999999
    }
  },
  {
    "kind": "NodeOp",
    "label": "SN_Start",
    "parameters": {}
  },
  {
    "kind": "EdgeOp",
    "label": "Coincident",
    "references": "(14, 0)",
    "parameters": {}
  },
  {
    "kind": "NodeOp",
    "label": "SN_End",
    "parameters": {}
  },
  {
    "kind": "NodeOp",
    "label": "Line",
    "parameters": {
      "isConstruction": false,
      "dirX": 1.0,
      "dirY": 0.0,
      "pntX": 0.004457235932350152,
      "pntY": -0.15000000000000002,
      "startParam": -0.10999999999999999,
      "endParam": 0.10999999999999999
    }
  },
  {
    "kind": "EdgeOp",
    "label": "Parallel",
    "references": "(16, 13)",
    "parameters": {}
  },
  {
    "kind": "EdgeOp",
    "label": "Horizontal",
    "references": "(16,)",
    "parameters": {}
  },
  {
    "kind": "NodeOp",
    "label": "SN_Start",
    "parameters": {}
  },
  {
    "kind": "NodeOp",
    "label": "SN_End",
    "parameters": {}
  },
  {
    "kind": "EdgeOp",
    "label": "Coincident",
    "references": "(18, 0)",
    "parameters": {}
  },
  {
    "kind": "NodeOp",
    "label": "Line",
    "parameters": {
      "isConstruction": false,
      "dirX": 0.0,
      "dirY": 1.0,
      "pntX": -0.10554276406764984,
      "pntY": -0.156010526239872,
      "startParam": -0.0029894737601280086,
      "endParam": 0.006010526239871972
    }
  },
  {
    "kind": "EdgeOp",
    "label": "Perpendicular",
    "references": "(19, 16)",
    "parameters": {}
  },
  {
    "kind": "NodeOp",
    "label": "SN_Start",
    "parameters": {}
  },
  {
    "kind": "EdgeOp",
    "label": "Coincident",
    "references": "(20, 14)",
    "parameters": {}
  },
  {
    "kind": "NodeOp",
    "label": "SN_End",
    "parameters": {}
  },
  {
    "kind": "EdgeOp",
    "label": "Coincident",
    "references": "(21, 17)",
    "parameters": {}
  },
  {
    "kind": "NodeOp",
    "label": "Line",
    "parameters": {
      "isConstruction": false,
      "dirX": 0.0,
      "dirY": 1.0,
      "pntX": 0.11445723593235015,
      "pntY": -0.156010526239872,
      "startParam": -0.0029894737601280086,
      "endParam": 0.006010526239871972
    }
  },
  {
    "kind": "EdgeOp",
    "label": "Parallel",
    "references": "(22, 19)",
    "parameters": {}
  },
  {
    "kind": "NodeOp",
    "label": "SN_Start",
    "parameters": {}
  },
  {
    "kind": "EdgeOp",
    "label": "Coincident",
    "references": "(23, 15)",
    "parameters": {}
  },
  {
    "kind": "NodeOp",
    "label": "SN_End",
    "parameters": {}
  },
  {
    "kind": "EdgeOp",
    "label": "Coincident",
    "references": "(24, 18)",
    "parameters": {}
  },
  {
    "kind": "NodeOp",
    "label": "Stop",
    "parameters": {}
  }
]